README.txt
setup.py
gremlinrestclient/__init__.py
gremlinrestclient/client.py
gremlinrestclient/exceptions.py
gremlinrestclient/graph.py
gremlinrestclient.egg-info/PKG-INFO
gremlinrestclient.egg-info/SOURCES.txt
gremlinrestclient.egg-info/dependency_links.txt
gremlinrestclient.egg-info/requires.txt
gremlinrestclient.egg-info/top_level.txt
tests/__init__.py
tests/tests.py