Metadata-Version: 1.1
Name: gremlinrestclient
Version: 0.0.10
Summary: Python client for Gremlin Server REST endpoint
Home-page: UNKNOWN
Author: davebshow
Author-email: davebshow@gmail.com
License: MIT
Platform: UNKNOWN
Classifier: Development Status :: 3 - Alpha
Classifier: Intended Audience :: Developers
Classifier: License :: OSI Approved :: MIT License
Classifier: Operating System :: OS Independent
Classifier: Programming Language :: Python
